nucleus_api/__init__.py
nucleus_api/api_client.py
nucleus_api/configuration.py
nucleus_api/rest.py
nucleus_api/api/__init__.py
nucleus_api/api/nucleus_api.py
nucleus_api/models/__init__.py
nucleus_api/models/admin_add_user_model.py
nucleus_api/models/admin_add_user_resp_model.py
nucleus_api/models/admin_delete_user_model.py
nucleus_api/models/admin_delete_user_resp_model.py
nucleus_api/models/admin_list_model.py
nucleus_api/models/admin_list_resp_model.py
nucleus_api/models/admin_manage_dataset_model.py
nucleus_api/models/admin_manage_dataset_resp_model.py
nucleus_api/models/admin_update_user_model.py
nucleus_api/models/admin_update_user_resp_model.py
nucleus_api/models/api_call.py
nucleus_api/models/append_json_resp_model.py
nucleus_api/models/appendjsonparams.py
nucleus_api/models/author_connect_l1_resp_model.py
nucleus_api/models/author_connect_l2_resp_model.py
nucleus_api/models/author_connect_resp_model.py
nucleus_api/models/author_connection.py
nucleus_api/models/available_filings_response_model.py
nucleus_api/models/bulk_insert_params.py
nucleus_api/models/bulk_insert_resp_model.py
nucleus_api/models/create_sec_dataset_response_model.py
nucleus_api/models/custom_tracker_l1_resp_model.py
nucleus_api/models/custom_tracker_model.py
nucleus_api/models/custom_tracker_resp_model.py
nucleus_api/models/dataset_info.py
nucleus_api/models/dataset_info_model.py
nucleus_api/models/dataset_info_resp_model.py
nucleus_api/models/dataset_resp_model.py
nucleus_api/models/dataset_tagging.py
nucleus_api/models/dataset_tagging_l1_resp_model.py
nucleus_api/models/dataset_tagging_resp_model.py
nucleus_api/models/delete_dataset_model.py
nucleus_api/models/delete_dataset_resp_model.py
nucleus_api/models/delete_document_model.py
nucleus_api/models/delete_document_resp_model.py
nucleus_api/models/delete_filter_model.py
nucleus_api/models/delete_filter_resp_model.py
nucleus_api/models/delete_forensic_model.py
nucleus_api/models/delete_forensic_resp_model.py
nucleus_api-4.0.9.dist-info/METADATA
nucleus_api-4.0.9.dist-info/WHEEL
nucleus_api-4.0.9.dist-info/top_level.txt
nucleus_api-4.0.9.dist-info/RECORD
